Metadata-Version: 2.1
Name: odoo14-addon-l10n_br_nfse_focus
Version: 14.0.1.8.0
Summary: NFS-e (FocusNFE)
Home-page: https://github.com/OCA/l10n-brazil
Author: KMEE, Escodoo, Odoo Community Association (OCA)
Author-email: support@odoo-community.org
License: AGPL-3
Classifier: Programming Language :: Python
Classifier: Framework :: Odoo
Classifier: Framework :: Odoo :: 14.0
Classifier: License :: OSI Approved :: GNU Affero General Public License v3
Classifier: Development Status :: 4 - Beta
Requires-Python: >=3.6
Requires-Dist: odoo14-addon-l10n-br-nfse
Requires-Dist: odoo<14.1dev,>=14.0a
